{"nodes":[{"name":"getCounterAbility","highlight":"f","group":0,"y":387,"x":240},{"name":"getNameAbility","highlight":"f","group":1,"y":548,"x":311},{"name":"getCounterNature","highlight":"f","group":1,"y":152,"x":719},{"name":"getInc","highlight":"f","group":2,"y":395,"x":194},{"name":"getDec","highlight":"f","group":2,"y":330,"x":887},{"name":"getAttackMod","highlight":"f","group":2,"y":273,"x":231},{"name":"getDefenceMod","highlight":"f","group":2,"y":233,"x":331},{"name":"getSpAttackMod","highlight":"f","group":2,"y":231,"x":786},{"name":"getSpDefenceMod","highlight":"f","group":2,"y":160,"x":609},{"name":"getSpeedMod","highlight":"f","group":2,"y":428,"x":277},{"name":"getCounterStatus","highlight":"f","group":2,"y":531,"x":760},{"name":"toString","highlight":"f","group":3,"y":265,"x":474},{"name":"addAttackIneffective","highlight":"f","group":4,"y":397,"x":353},{"name":"addAttackImmune","highlight":"f","group":4,"y":452,"x":676},{"name":"addDefendEffective","highlight":"f","group":4,"y":465,"x":702},{"name":"addDefendImmune","highlight":"f","group":4,"y":224,"x":293},{"name":"addAttackEffective","highlight":"f","group":4,"y":497,"x":853},{"name":"addDefendIneffective","highlight":"f","group":4,"y":427,"x":763},{"name":"getNameType","highlight":"f","group":4,"y":227,"x":377},{"name":"getAttackEffective","highlight":"f","group":4,"y":227,"x":637},{"name":"getAttackIneffective","highlight":"f","group":4,"y":278,"x":281},{"name":"getAttackImmune","highlight":"f","group":4,"y":207,"x":223},{"name":"getDefendEffective","highlight":"f","group":4,"y":534,"x":283},{"name":"getDefendIneffective","highlight":"f","group":4,"y":239,"x":226},{"name":"getDefendImmune","highlight":"f","group":4,"y":170,"x":362},{"name":"isSpecial","highlight":"f","group":4,"y":221,"x":939},{"name":"isGrounded","highlight":"f","group":4,"y":280,"x":653},{"name":"getStatusImmunities","highlight":"f","group":4,"y":215,"x":281},{"name":"getWeatherImmunities","highlight":"f","group":4,"y":339,"x":198},{"name":"getCounterType","highlight":"f","group":4,"y":271,"x":475},{"name":"getPriority","highlight":"f","group":4,"y":232,"x":943},{"name":"getType","highlight":"f","group":5,"y":185,"x":763},{"name":"getCounterMove","highlight":"f","group":5,"y":194,"x":703},{"name":"setFlags","highlight":"f","group":5,"y":172,"x":307},{"name":"getNameMove","highlight":"f","group":5,"y":485,"x":933},{"name":"getCategory","highlight":"f","group":5,"y":430,"x":659},{"name":"getPower","highlight":"f","group":5,"y":303,"x":651},{"name":"getAccuracy","highlight":"f","group":5,"y":386,"x":960},{"name":"getEffect","highlight":"f","group":5,"y":311,"x":324},{"name":"getEffectAccuracy","highlight":"f","group":5,"y":259,"x":916},{"name":"getPp","highlight":"f","group":5,"y":365,"x":903},{"name":"isContact","highlight":"f","group":5,"y":481,"x":924},{"name":"isProtect","highlight":"f","group":5,"y":471,"x":770},{"name":"isMagicCoat","highlight":"f","group":5,"y":295,"x":354},{"name":"isSnatch","highlight":"f","group":5,"y":215,"x":329},{"name":"isMirrorMove","highlight":"f","group":5,"y":274,"x":258},{"name":"isKingsRock","highlight":"f","group":5,"y":399,"x":909},{"name":"isCriticalHit","highlight":"f","group":5,"y":295,"x":1020},{"name":"getStatUpsSelf","highlight":"f","group":5,"y":373,"x":305},{"name":"getStatDownsSelf","highlight":"f","group":5,"y":436,"x":1025},{"name":"getStatUpsFoe","highlight":"f","group":5,"y":362,"x":497},{"name":"getStatDownsFoe","highlight":"f","group":5,"y":339,"x":843},{"name":"getStatAccuracy","highlight":"f","group":5,"y":399,"x":803},{"name":"useMove","highlight":"t","group":5,"y":543,"x":731},{"name":"getExpectedDamage","highlight":"f","group":5,"y":443,"x":669},{"name":"isStatMove","highlight":"f","group":5,"y":409,"x":548},{"name":"isStatusMove","highlight":"f","group":5,"y":337,"x":371},{"name":"getFlinchAccuracy","highlight":"f","group":5,"y":236,"x":614},{"name":"getCounterSpecies","highlight":"f","group":5,"y":220,"x":985},{"name":"getType1","highlight":"f","group":6,"y":325,"x":479},{"name":"getType2","highlight":"f","group":6,"y":244,"x":1023},{"name":"setStats","highlight":"f","group":6,"y":191,"x":1044},{"name":"setHP","highlight":"f","group":6,"y":248,"x":450},{"name":"setAttack","highlight":"f","group":6,"y":406,"x":690},{"name":"setDefence","highlight":"f","group":6,"y":440,"x":315},{"name":"setSpeed","highlight":"f","group":6,"y":386,"x":512},{"name":"setSpAttack","highlight":"f","group":6,"y":190,"x":1008},{"name":"setSpDefence","highlight":"f","group":6,"y":341,"x":586},{"name":"getHP","highlight":"f","group":6,"y":502,"x":383},{"name":"getAttack","highlight":"f","group":6,"y":493,"x":396},{"name":"getDefence","highlight":"f","group":6,"y":200,"x":770},{"name":"getSpeed","highlight":"f","group":6,"y":172,"x":325},{"name":"getSpAttack","highlight":"f","group":6,"y":252,"x":160},{"name":"getSpDefence","highlight":"f","group":6,"y":398,"x":877},{"name":"toString","highlight":"f","group":6,"y":320,"x":229},{"name":"getName","highlight":"f","group":7,"y":213,"x":647},{"name":"reset","highlight":"f","group":7,"y":444,"x":896},{"name":"getCounterPkmn","highlight":"f","group":7,"y":440,"x":497},{"name":"getAttackMod","highlight":"f","group":7,"y":186,"x":694},{"name":"getDefenceMod","highlight":"f","group":7,"y":461,"x":443},{"name":"getSpAttackMod","highlight":"f","group":7,"y":236,"x":271},{"name":"getSpDefenceMod","highlight":"f","group":7,"y":395,"x":180},{"name":"getSpeedMod","highlight":"f","group":7,"y":534,"x":707},{"name":"getModifiedAccuracy","highlight":"f","group":7,"y":362,"x":320},{"name":"getModifiedEvasion","highlight":"f","group":7,"y":464,"x":630},{"name":"incSpeedMod","highlight":"f","group":7,"y":164,"x":700},{"name":"heal","highlight":"f","group":7,"y":382,"x":276},{"name":"incAttackMod","highlight":"f","group":7,"y":234,"x":904},{"name":"getStatus","highlight":"f","group":7,"y":157,"x":1017},{"name":"setStatus","highlight":"f","group":7,"y":354,"x":1014},{"name":"setBadPsnCounter","highlight":"f","group":7,"y":183,"x":706},{"name":"incDefenceMod","highlight":"f","group":7,"y":510,"x":416},{"name":"incSpAttackMod","highlight":"f","group":7,"y":495,"x":349},{"name":"incSpDefenceMod","highlight":"f","group":7,"y":440,"x":874},{"name":"incAccuracyMod","highlight":"f","group":7,"y":540,"x":983},{"name":"incEvasionMod","highlight":"f","group":7,"y":183,"x":997},{"name":"decAttackMod","highlight":"f","group":7,"y":320,"x":855},{"name":"decDefenceMod","highlight":"f","group":7,"y":223,"x":233},{"name":"decSpAttackMod","highlight":"f","group":7,"y":280,"x":913},{"name":"decSpDefenceMod","highlight":"f","group":7,"y":513,"x":405},{"name":"decSpeedMod","highlight":"f","group":7,"y":172,"x":810},{"name":"decAccuracyMod","highlight":"f","group":7,"y":419,"x":709},{"name":"decEvasionMod","highlight":"f","group":7,"y":268,"x":680},{"name":"getModifiedAttack","highlight":"f","group":7,"y":478,"x":840},{"name":"getModifiedDefence","highlight":"f","group":7,"y":357,"x":550},{"name":"getModifiedSpAttack","highlight":"f","group":7,"y":442,"x":848},{"name":"getModifiedSpDefence","highlight":"f","group":7,"y":505,"x":575},{"name":"damage","highlight":"f","group":7,"y":301,"x":493},{"name":"setFlinch","highlight":"f","group":7,"y":335,"x":631},{"name":"setFlinch","highlight":"f","group":7,"y":226,"x":1026},{"name":"getLevel","highlight":"f","group":7,"y":154,"x":947},{"name":"getSpecies","highlight":"f","group":7,"y":447,"x":909},{"name":"getCurrHP","highlight":"f","group":7,"y":352,"x":290},{"name":"getSleepCounter","highlight":"f","group":7,"y":285,"x":1016},{"name":"setSleepCounter","highlight":"f","group":7,"y":218,"x":516},{"name":"getBadPsnCounter","highlight":"f","group":7,"y":424,"x":660},{"name":"isFlinch","highlight":"f","group":7,"y":511,"x":280},{"name":"initialiseStats","highlight":"f","group":7,"y":151,"x":889},{"name":"setAbility","highlight":"f","group":7,"y":395,"x":447},{"name":"getAbility","highlight":"f","group":7,"y":164,"x":541},{"name":"setMoveset4","highlight":"f","group":7,"y":350,"x":818},{"name":"setMove4","highlight":"f","group":7,"y":237,"x":417},{"name":"setMoveset3","highlight":"f","group":7,"y":307,"x":586},{"name":"setMove3","highlight":"f","group":7,"y":172,"x":717},{"name":"setMoveset2","highlight":"f","group":7,"y":511,"x":971},{"name":"setMove2","highlight":"f","group":7,"y":317,"x":349},{"name":"setMoveset1","highlight":"f","group":7,"y":382,"x":182},{"name":"setMove1","highlight":"f","group":7,"y":511,"x":656},{"name":"getTotalHP","highlight":"f","group":7,"y":476,"x":693},{"name":"getIVHP","highlight":"f","group":7,"y":425,"x":788},{"name":"setIVHP","highlight":"f","group":7,"y":291,"x":498},{"name":"getIVA","highlight":"f","group":7,"y":498,"x":342},{"name":"setIVA","highlight":"f","group":7,"y":283,"x":307},{"name":"getIVD","highlight":"f","group":7,"y":273,"x":589},{"name":"setIVD","highlight":"f","group":7,"y":422,"x":385},{"name":"getIVS","highlight":"f","group":7,"y":316,"x":704},{"name":"setIVS","highlight":"f","group":7,"y":158,"x":479},{"name":"getIVSA","highlight":"f","group":7,"y":303,"x":867},{"name":"setIVSA","highlight":"f","group":7,"y":276,"x":888},{"name":"getIVSD","highlight":"f","group":7,"y":401,"x":443},{"name":"setIVSD","highlight":"f","group":7,"y":418,"x":439},{"name":"setAllEVs","highlight":"f","group":7,"y":367,"x":472},{"name":"setEVHP","highlight":"f","group":7,"y":216,"x":817},{"name":"setEVA","highlight":"f","group":7,"y":337,"x":518},{"name":"setEVD","highlight":"f","group":7,"y":370,"x":880},{"name":"setEVSA","highlight":"f","group":7,"y":194,"x":401},{"name":"setEVSD","highlight":"f","group":7,"y":474,"x":832},{"name":"setEVS","highlight":"f","group":7,"y":306,"x":767},{"name":"getEVHP","highlight":"f","group":7,"y":506,"x":530},{"name":"getEVA","highlight":"f","group":7,"y":493,"x":769},{"name":"getEVD","highlight":"f","group":7,"y":266,"x":766},{"name":"getEVS","highlight":"f","group":7,"y":470,"x":406},{"name":"getEVSA","highlight":"f","group":7,"y":261,"x":404},{"name":"getEVSD","highlight":"f","group":7,"y":263,"x":988},{"name":"getAccuracyMod","highlight":"f","group":7,"y":521,"x":340},{"name":"getEvasionMod","highlight":"f","group":7,"y":288,"x":1026},{"name":"calculateModFactor","highlight":"f","group":7,"y":401,"x":319},{"name":"calculateModFactorAcc","highlight":"f","group":7,"y":535,"x":883},{"name":"getModifiedSpeed","highlight":"f","group":7,"y":407,"x":1034},{"name":"resetMods","highlight":"f","group":7,"y":313,"x":796},{"name":"getMove","highlight":"f","group":7,"y":518,"x":580},{"name":"hasMove","highlight":"f","group":7,"y":540,"x":220},{"name":"getPP","highlight":"f","group":7,"y":208,"x":659},{"name":"useMoveIndex","highlight":"f","group":7,"y":441,"x":658},{"name":"useMoveFromPkmn","highlight":"f","group":7,"y":405,"x":545},{"name":"faint","highlight":"f","group":7,"y":363,"x":717},{"name":"printObj","highlight":"f","group":7,"y":286,"x":489},{"name":"printObjStats","highlight":"f","group":7,"y":446,"x":590},{"name":"printObjMoves","highlight":"f","group":7,"y":190,"x":152},{"name":"getCounterWeather","highlight":"f","group":7,"y":228,"x":285},{"name":"chooseMove","highlight":"f","group":8,"y":298,"x":547},{"name":"isBattleOver","highlight":"f","group":9,"y":401,"x":590},{"name":"oneBattle","highlight":"f","group":9,"y":521,"x":695},{"name":"allBattles","highlight":"f","group":9,"y":452,"x":608},{"name":"runBattles","highlight":"f","group":9,"y":381,"x":549},{"name":"chooseStrongestPriorityMove","highlight":"f","group":9,"y":420,"x":508},{"name":"chooseStrongestMove","highlight":"f","group":9,"y":466,"x":567},{"name":"chooseRandomStatusMove","highlight":"f","group":9,"y":512,"x":1003},{"name":"chooseRandomStatMove","highlight":"f","group":9,"y":443,"x":818},{"name":"chooseRandomMove","highlight":"f","group":9,"y":275,"x":399},{"name":"getCounterGenVSim","highlight":"f","group":9,"y":412,"x":356},{"name":"mainFile","highlight":"f","group":9,"y":216,"x":687},{"name":"generatePayoffMatrix","highlight":"f","group":10,"y":466,"x":995},{"name":"matrixToString","highlight":"f","group":10,"y":460,"x":1014}],"links":[{"source":53,"value":1,"target":83},{"source":53,"value":1,"target":84},{"source":53,"value":1,"target":85},{"source":53,"value":1,"target":86},{"source":53,"value":1,"target":86},{"source":53,"value":1,"target":87},{"source":53,"value":1,"target":89},{"source":53,"value":1,"target":90},{"source":53,"value":1,"target":89},{"source":53,"value":1,"target":87},{"source":53,"value":1,"target":91},{"source":53,"value":1,"target":92},{"source":53,"value":1,"target":93},{"source":53,"value":1,"target":85},{"source":53,"value":1,"target":94},{"source":53,"value":1,"target":95},{"source":53,"value":1,"target":96},{"source":53,"value":1,"target":97},{"source":53,"value":1,"target":98},{"source":53,"value":1,"target":99},{"source":53,"value":1,"target":100},{"source":53,"value":1,"target":101},{"source":53,"value":1,"target":102},{"source":53,"value":1,"target":87},{"source":53,"value":1,"target":91},{"source":53,"value":1,"target":92},{"source":53,"value":1,"target":93},{"source":53,"value":1,"target":85},{"source":53,"value":1,"target":94},{"source":53,"value":1,"target":95},{"source":53,"value":1,"target":96},{"source":53,"value":1,"target":97},{"source":53,"value":1,"target":98},{"source":53,"value":1,"target":99},{"source":53,"value":1,"target":100},{"source":53,"value":1,"target":101},{"source":53,"value":1,"target":102},{"source":53,"value":1,"target":103},{"source":53,"value":1,"target":104},{"source":53,"value":1,"target":105},{"source":53,"value":1,"target":106},{"source":53,"value":1,"target":92},{"source":53,"value":1,"target":85},{"source":53,"value":1,"target":86},{"source":53,"value":1,"target":86},{"source":53,"value":1,"target":87},{"source":53,"value":1,"target":107},{"source":53,"value":1,"target":87},{"source":53,"value":1,"target":85},{"source":53,"value":1,"target":85},{"source":53,"value":1,"target":97},{"source":53,"value":1,"target":109},{"source":53,"value":1,"target":85},{"source":53,"value":1,"target":89},{"source":53,"value":1,"target":89},{"source":53,"value":1,"target":87},{"source":53,"value":1,"target":91},{"source":53,"value":1,"target":92},{"source":53,"value":1,"target":93},{"source":53,"value":1,"target":85},{"source":53,"value":1,"target":94},{"source":53,"value":1,"target":95},{"source":53,"value":1,"target":96},{"source":53,"value":1,"target":97},{"source":53,"value":1,"target":98},{"source":53,"value":1,"target":99},{"source":53,"value":1,"target":100},{"source":53,"value":1,"target":101},{"source":53,"value":1,"target":102},{"source":53,"value":1,"target":87},{"source":53,"value":1,"target":91},{"source":53,"value":1,"target":92},{"source":53,"value":1,"target":93},{"source":53,"value":1,"target":85},{"source":53,"value":1,"target":94},{"source":53,"value":1,"target":95},{"source":53,"value":1,"target":96},{"source":53,"value":1,"target":97},{"source":53,"value":1,"target":98},{"source":53,"value":1,"target":99},{"source":53,"value":1,"target":100},{"source":53,"value":1,"target":100},{"source":53,"value":1,"target":102},{"source":54,"value":1,"target":83},{"source":54,"value":1,"target":84},{"source":54,"value":1,"target":110},{"source":54,"value":1,"target":36},{"source":54,"value":1,"target":60},{"source":54,"value":1,"target":60},{"source":54,"value":1,"target":35},{"source":54,"value":1,"target":103},{"source":54,"value":1,"target":104},{"source":54,"value":1,"target":105},{"source":54,"value":1,"target":106},{"source":117,"value":1,"target":68},{"source":117,"value":1,"target":69},{"source":117,"value":1,"target":78},{"source":117,"value":1,"target":70},{"source":117,"value":1,"target":79},{"source":117,"value":1,"target":71},{"source":117,"value":1,"target":82},{"source":117,"value":1,"target":72},{"source":117,"value":1,"target":80},{"source":117,"value":1,"target":73},{"source":117,"value":1,"target":81},{"source":120,"value":1,"target":121},{"source":120,"value":1,"target":122},{"source":122,"value":1,"target":123},{"source":122,"value":1,"target":124},{"source":124,"value":1,"target":125},{"source":124,"value":1,"target":126},{"source":126,"value":1,"target":127},{"source":141,"value":1,"target":142},{"source":141,"value":1,"target":143},{"source":141,"value":1,"target":144},{"source":141,"value":1,"target":145},{"source":141,"value":1,"target":146},{"source":141,"value":1,"target":147},{"source":103,"value":1,"target":156},{"source":104,"value":1,"target":156},{"source":105,"value":1,"target":156},{"source":106,"value":1,"target":156},{"source":158,"value":1,"target":156},{"source":83,"value":1,"target":157},{"source":84,"value":1,"target":157},{"source":163,"value":1,"target":164},{"source":163,"value":1,"target":164},{"source":163,"value":1,"target":164},{"source":163,"value":1,"target":164},{"source":163,"value":1,"target":53},{"source":164,"value":1,"target":53},{"source":107,"value":1,"target":165},{"source":76,"value":1,"target":159},{"source":166,"value":1,"target":74},{"source":167,"value":1,"target":166},{"source":168,"value":1,"target":166},{"source":61,"value":1,"target":62},{"source":61,"value":1,"target":63},{"source":61,"value":1,"target":64},{"source":61,"value":1,"target":65},{"source":61,"value":1,"target":66},{"source":61,"value":1,"target":67},{"source":181,"value":1,"target":122},{"source":181,"value":1,"target":118},{"source":181,"value":1,"target":141},{"source":181,"value":1,"target":120},{"source":181,"value":1,"target":118},{"source":181,"value":1,"target":141},{"source":181,"value":1,"target":120},{"source":181,"value":1,"target":118},{"source":181,"value":1,"target":141},{"source":181,"value":1,"target":120},{"source":181,"value":1,"target":120},{"source":181,"value":1,"target":141},{"source":181,"value":1,"target":122},{"source":181,"value":1,"target":120},{"source":181,"value":1,"target":118},{"source":181,"value":1,"target":141},{"source":181,"value":1,"target":120},{"source":181,"value":1,"target":118},{"source":181,"value":1,"target":141},{"source":181,"value":1,"target":120},{"source":181,"value":1,"target":118},{"source":181,"value":1,"target":141},{"source":181,"value":1,"target":120},{"source":181,"value":1,"target":118},{"source":181,"value":1,"target":130},{"source":181,"value":1,"target":141},{"source":181,"value":1,"target":120},{"source":181,"value":1,"target":118},{"source":181,"value":1,"target":141},{"source":181,"value":1,"target":120},{"source":181,"value":1,"target":118},{"source":181,"value":1,"target":141},{"source":181,"value":1,"target":120},{"source":181,"value":1,"target":118},{"source":181,"value":1,"target":141},{"source":181,"value":1,"target":120},{"source":181,"value":1,"target":118},{"source":181,"value":1,"target":141},{"source":181,"value":1,"target":120},{"source":181,"value":1,"target":118},{"source":181,"value":1,"target":132},{"source":181,"value":1,"target":138},{"source":181,"value":1,"target":141},{"source":181,"value":1,"target":126},{"source":181,"value":1,"target":120},{"source":181,"value":1,"target":141},{"source":181,"value":1,"target":120},{"source":181,"value":1,"target":118},{"source":181,"value":1,"target":141},{"source":181,"value":1,"target":120},{"source":181,"value":1,"target":118},{"source":181,"value":1,"target":141},{"source":181,"value":1,"target":120},{"source":181,"value":1,"target":118},{"source":181,"value":1,"target":141},{"source":181,"value":1,"target":120},{"source":181,"value":1,"target":118},{"source":181,"value":1,"target":141},{"source":181,"value":1,"target":120},{"source":181,"value":1,"target":118},{"source":181,"value":1,"target":141},{"source":181,"value":1,"target":122},{"source":181,"value":1,"target":141},{"source":181,"value":1,"target":120},{"source":181,"value":1,"target":118},{"source":181,"value":1,"target":141},{"source":181,"value":1,"target":120},{"source":181,"value":1,"target":118},{"source":181,"value":1,"target":141},{"source":181,"value":1,"target":120},{"source":181,"value":1,"target":118},{"source":181,"value":1,"target":141},{"source":181,"value":1,"target":120},{"source":181,"value":1,"target":118},{"source":181,"value":1,"target":141},{"source":181,"value":1,"target":120},{"source":181,"value":1,"target":118},{"source":181,"value":1,"target":141},{"source":181,"value":1,"target":120},{"source":181,"value":1,"target":141},{"source":181,"value":1,"target":120},{"source":181,"value":1,"target":141},{"source":181,"value":1,"target":120},{"source":181,"value":1,"target":118},{"source":181,"value":1,"target":141},{"source":181,"value":1,"target":120},{"source":181,"value":1,"target":118},{"source":181,"value":1,"target":141},{"source":181,"value":1,"target":120},{"source":181,"value":1,"target":118},{"source":181,"value":1,"target":130},{"source":181,"value":1,"target":141},{"source":181,"value":1,"target":122},{"source":181,"value":1,"target":141},{"source":181,"value":1,"target":120},{"source":181,"value":1,"target":141},{"source":181,"value":1,"target":124},{"source":181,"value":1,"target":120},{"source":181,"value":1,"target":118},{"source":181,"value":1,"target":141},{"source":181,"value":1,"target":120},{"source":181,"value":1,"target":118},{"source":181,"value":1,"target":141},{"source":181,"value":1,"target":120},{"source":181,"value":1,"target":118},{"source":181,"value":1,"target":141},{"source":181,"value":1,"target":122},{"source":181,"value":1,"target":118},{"source":181,"value":1,"target":124},{"source":181,"value":1,"target":141},{"source":181,"value":1,"target":124},{"source":181,"value":1,"target":118},{"source":181,"value":1,"target":122},{"source":181,"value":1,"target":118},{"source":181,"value":1,"target":141},{"source":181,"value":1,"target":120},{"source":181,"value":1,"target":118},{"source":181,"value":1,"target":130},{"source":181,"value":1,"target":141},{"source":181,"value":1,"target":120},{"source":181,"value":1,"target":118},{"source":181,"value":1,"target":130},{"source":181,"value":1,"target":141},{"source":181,"value":1,"target":120},{"source":181,"value":1,"target":118},{"source":181,"value":1,"target":141},{"source":181,"value":1,"target":120},{"source":181,"value":1,"target":118},{"source":181,"value":1,"target":141},{"source":181,"value":1,"target":120},{"source":181,"value":1,"target":118},{"source":181,"value":1,"target":141},{"source":181,"value":1,"target":120},{"source":181,"value":1,"target":118},{"source":181,"value":1,"target":141},{"source":181,"value":1,"target":124},{"source":181,"value":1,"target":118},{"source":181,"value":1,"target":141},{"source":181,"value":1,"target":124},{"source":181,"value":1,"target":141},{"source":181,"value":1,"target":122},{"source":181,"value":1,"target":118},{"source":181,"value":1,"target":141},{"source":181,"value":1,"target":120},{"source":181,"value":1,"target":118},{"source":181,"value":1,"target":141},{"source":181,"value":1,"target":120},{"source":181,"value":1,"target":118},{"source":181,"value":1,"target":141},{"source":181,"value":1,"target":120},{"source":181,"value":1,"target":118},{"source":181,"value":1,"target":138},{"source":181,"value":1,"target":140},{"source":181,"value":1,"target":136},{"source":181,"value":1,"target":141},{"source":181,"value":1,"target":122},{"source":181,"value":1,"target":120},{"source":181,"value":1,"target":118},{"source":181,"value":1,"target":141},{"source":181,"value":1,"target":120},{"source":181,"value":1,"target":118},{"source":181,"value":1,"target":141},{"source":181,"value":1,"target":120},{"source":181,"value":1,"target":118},{"source":181,"value":1,"target":130},{"source":181,"value":1,"target":141},{"source":181,"value":1,"target":120},{"source":181,"value":1,"target":118},{"source":181,"value":1,"target":130},{"source":181,"value":1,"target":141},{"source":181,"value":1,"target":120},{"source":181,"value":1,"target":118},{"source":181,"value":1,"target":130},{"source":181,"value":1,"target":141},{"source":181,"value":1,"target":120},{"source":181,"value":1,"target":118},{"source":181,"value":1,"target":141},{"source":181,"value":1,"target":120},{"source":181,"value":1,"target":126},{"source":181,"value":1,"target":120},{"source":181,"value":1,"target":118},{"source":181,"value":1,"target":141},{"source":181,"value":1,"target":120},{"source":181,"value":1,"target":118},{"source":181,"value":1,"target":141},{"source":181,"value":1,"target":122},{"source":181,"value":1,"target":118},{"source":181,"value":1,"target":141},{"source":181,"value":1,"target":124},{"source":181,"value":1,"target":120},{"source":181,"value":1,"target":120},{"source":181,"value":1,"target":118},{"source":181,"value":1,"target":141},{"source":181,"value":1,"target":120},{"source":181,"value":1,"target":118},{"source":181,"value":1,"target":141},{"source":181,"value":1,"target":120},{"source":181,"value":1,"target":118},{"source":181,"value":1,"target":141},{"source":181,"value":1,"target":120},{"source":181,"value":1,"target":118},{"source":181,"value":1,"target":141},{"source":181,"value":1,"target":120},{"source":181,"value":1,"target":118},{"source":181,"value":1,"target":141},{"source":181,"value":1,"target":122},{"source":181,"value":1,"target":120},{"source":181,"value":1,"target":141},{"source":181,"value":1,"target":120},{"source":181,"value":1,"target":118},{"source":181,"value":1,"target":141},{"source":181,"value":1,"target":120},{"source":181,"value":1,"target":118},{"source":181,"value":1,"target":141},{"source":181,"value":1,"target":120},{"source":181,"value":1,"target":118},{"source":181,"value":1,"target":130},{"source":181,"value":1,"target":132},{"source":181,"value":1,"target":138},{"source":181,"value":1,"target":136},{"source":181,"value":1,"target":141},{"source":181,"value":1,"target":120},{"source":181,"value":1,"target":118},{"source":181,"value":1,"target":141},{"source":181,"value":1,"target":120},{"source":181,"value":1,"target":118},{"source":181,"value":1,"target":141},{"source":181,"value":1,"target":120},{"source":181,"value":1,"target":130},{"source":181,"value":1,"target":141},{"source":181,"value":1,"target":120},{"source":181,"value":1,"target":118},{"source":181,"value":1,"target":132},{"source":181,"value":1,"target":138},{"source":181,"value":1,"target":136},{"source":181,"value":1,"target":141},{"source":181,"value":1,"target":122},{"source":181,"value":1,"target":118},{"source":181,"value":1,"target":141},{"source":181,"value":1,"target":120},{"source":181,"value":1,"target":118},{"source":181,"value":1,"target":141},{"source":181,"value":1,"target":120},{"source":181,"value":1,"target":141},{"source":181,"value":1,"target":120},{"source":181,"value":1,"target":141},{"source":181,"value":1,"target":120},{"source":181,"value":1,"target":141},{"source":181,"value":1,"target":120},{"source":181,"value":1,"target":118},{"source":181,"value":1,"target":141},{"source":181,"value":1,"target":120},{"source":181,"value":1,"target":118},{"source":181,"value":1,"target":141},{"source":181,"value":1,"target":120},{"source":181,"value":1,"target":118},{"source":181,"value":1,"target":141},{"source":181,"value":1,"target":120},{"source":181,"value":1,"target":141},{"source":181,"value":1,"target":120},{"source":181,"value":1,"target":141},{"source":181,"value":1,"target":120},{"source":181,"value":1,"target":141},{"source":181,"value":1,"target":120},{"source":181,"value":1,"target":118},{"source":181,"value":1,"target":141},{"source":181,"value":1,"target":122},{"source":181,"value":1,"target":122},{"source":181,"value":1,"target":118},{"source":181,"value":1,"target":141},{"source":181,"value":1,"target":120},{"source":181,"value":1,"target":118},{"source":181,"value":1,"target":141},{"source":181,"value":1,"target":120},{"source":181,"value":1,"target":118},{"source":181,"value":1,"target":141},{"source":181,"value":1,"target":120},{"source":181,"value":1,"target":118},{"source":181,"value":1,"target":141},{"source":181,"value":1,"target":120},{"source":181,"value":1,"target":120},{"source":181,"value":1,"target":141},{"source":181,"value":1,"target":120},{"source":181,"value":1,"target":141},{"source":181,"value":1,"target":120},{"source":181,"value":1,"target":141},{"source":181,"value":1,"target":120},{"source":181,"value":1,"target":118},{"source":181,"value":1,"target":141},{"source":181,"value":1,"target":120},{"source":181,"value":1,"target":118},{"source":181,"value":1,"target":141},{"source":181,"value":1,"target":120},{"source":181,"value":1,"target":118},{"source":181,"value":1,"target":141},{"source":181,"value":1,"target":120},{"source":181,"value":1,"target":118},{"source":181,"value":1,"target":141},{"source":181,"value":1,"target":120},{"source":181,"value":1,"target":141},{"source":181,"value":1,"target":122},{"source":181,"value":1,"target":118},{"source":181,"value":1,"target":141},{"source":181,"value":1,"target":122},{"source":181,"value":1,"target":118},{"source":181,"value":1,"target":141},{"source":181,"value":1,"target":120},{"source":181,"value":1,"target":118},{"source":181,"value":1,"target":141},{"source":181,"value":1,"target":120},{"source":181,"value":1,"target":118},{"source":181,"value":1,"target":141},{"source":181,"value":1,"target":120},{"source":181,"value":1,"target":118},{"source":181,"value":1,"target":141},{"source":181,"value":1,"target":120},{"source":181,"value":1,"target":141},{"source":181,"value":1,"target":120},{"source":181,"value":1,"target":118},{"source":181,"value":1,"target":141},{"source":181,"value":1,"target":120},{"source":181,"value":1,"target":118},{"source":181,"value":1,"target":141},{"source":181,"value":1,"target":122},{"source":181,"value":1,"target":120},{"source":181,"value":1,"target":118},{"source":181,"value":1,"target":141},{"source":181,"value":1,"target":120},{"source":181,"value":1,"target":118},{"source":181,"value":1,"target":141},{"source":181,"value":1,"target":120},{"source":181,"value":1,"target":118},{"source":181,"value":1,"target":141},{"source":181,"value":1,"target":120},{"source":181,"value":1,"target":118},{"source":181,"value":1,"target":141},{"source":181,"value":1,"target":122},{"source":181,"value":1,"target":118},{"source":181,"value":1,"target":141},{"source":181,"value":1,"target":122},{"source":181,"value":1,"target":118},{"source":181,"value":1,"target":141},{"source":181,"value":1,"target":120},{"source":181,"value":1,"target":118},{"source":181,"value":1,"target":136},{"source":181,"value":1,"target":141},{"source":181,"value":1,"target":120},{"source":181,"value":1,"target":118},{"source":181,"value":1,"target":141},{"source":181,"value":1,"target":122},{"source":181,"value":1,"target":120},{"source":181,"value":1,"target":118},{"source":181,"value":1,"target":141},{"source":181,"value":1,"target":122},{"source":181,"value":1,"target":118},{"source":181,"value":1,"target":141},{"source":181,"value":1,"target":120},{"source":181,"value":1,"target":141},{"source":181,"value":1,"target":120},{"source":181,"value":1,"target":118},{"source":181,"value":1,"target":141},{"source":181,"value":1,"target":120},{"source":181,"value":1,"target":141},{"source":181,"value":1,"target":124},{"source":181,"value":1,"target":120},{"source":181,"value":1,"target":118},{"source":181,"value":1,"target":141},{"source":181,"value":1,"target":120},{"source":181,"value":1,"target":141},{"source":181,"value":1,"target":120},{"source":181,"value":1,"target":141},{"source":181,"value":1,"target":120},{"source":181,"value":1,"target":118},{"source":181,"value":1,"target":141},{"source":181,"value":1,"target":120},{"source":181,"value":1,"target":134},{"source":181,"value":1,"target":138},{"source":181,"value":1,"target":140},{"source":181,"value":1,"target":136},{"source":181,"value":1,"target":141},{"source":181,"value":1,"target":120},{"source":181,"value":1,"target":118},{"source":181,"value":1,"target":141},{"source":181,"value":1,"target":122},{"source":181,"value":1,"target":118},{"source":181,"value":1,"target":141},{"source":181,"value":1,"target":120},{"source":181,"value":1,"target":118},{"source":181,"value":1,"target":130},{"source":181,"value":1,"target":141},{"source":181,"value":1,"target":120},{"source":181,"value":1,"target":118},{"source":181,"value":1,"target":130},{"source":181,"value":1,"target":141},{"source":181,"value":1,"target":120},{"source":181,"value":1,"target":118},{"source":181,"value":1,"target":141},{"source":181,"value":1,"target":120},{"source":181,"value":1,"target":118},{"source":181,"value":1,"target":141},{"source":181,"value":1,"target":120},{"source":181,"value":1,"target":118},{"source":181,"value":1,"target":130},{"source":181,"value":1,"target":141},{"source":181,"value":1,"target":120},{"source":181,"value":1,"target":118},{"source":181,"value":1,"target":141},{"source":181,"value":1,"target":120},{"source":181,"value":1,"target":141},{"source":181,"value":1,"target":120},{"source":181,"value":1,"target":118},{"source":181,"value":1,"target":141},{"source":181,"value":1,"target":120},{"source":181,"value":1,"target":120},{"source":181,"value":1,"target":130},{"source":181,"value":1,"target":132},{"source":181,"value":1,"target":138},{"source":181,"value":1,"target":136},{"source":181,"value":1,"target":141},{"source":181,"value":1,"target":120},{"source":181,"value":1,"target":141},{"source":181,"value":1,"target":120},{"source":181,"value":1,"target":118},{"source":181,"value":1,"target":141},{"source":181,"value":1,"target":120},{"source":181,"value":1,"target":118},{"source":181,"value":1,"target":141},{"source":181,"value":1,"target":120},{"source":181,"value":1,"target":118},{"source":181,"value":1,"target":141},{"source":181,"value":1,"target":120},{"source":181,"value":1,"target":118},{"source":181,"value":1,"target":141},{"source":181,"value":1,"target":120},{"source":181,"value":1,"target":118},{"source":181,"value":1,"target":141},{"source":181,"value":1,"target":120},{"source":181,"value":1,"target":118},{"source":181,"value":1,"target":141},{"source":181,"value":1,"target":124},{"source":181,"value":1,"target":122},{"source":181,"value":1,"target":118},{"source":181,"value":1,"target":130},{"source":181,"value":1,"target":132},{"source":181,"value":1,"target":138},{"source":181,"value":1,"target":141},{"source":181,"value":1,"target":120},{"source":181,"value":1,"target":118},{"source":181,"value":1,"target":141},{"source":181,"value":1,"target":120},{"source":181,"value":1,"target":118},{"source":181,"value":1,"target":141},{"source":181,"value":1,"target":120},{"source":181,"value":1,"target":118},{"source":181,"value":1,"target":130},{"source":181,"value":1,"target":136},{"source":181,"value":1,"target":141},{"source":181,"value":1,"target":120},{"source":181,"value":1,"target":118},{"source":181,"value":1,"target":141},{"source":181,"value":1,"target":120},{"source":181,"value":1,"target":118},{"source":181,"value":1,"target":130},{"source":181,"value":1,"target":141},{"source":181,"value":1,"target":124},{"source":181,"value":1,"target":124},{"source":181,"value":1,"target":120},{"source":181,"value":1,"target":120},{"source":181,"value":1,"target":120},{"source":181,"value":1,"target":120},{"source":181,"value":1,"target":141},{"source":181,"value":1,"target":120},{"source":181,"value":1,"target":118},{"source":181,"value":1,"target":130},{"source":181,"value":1,"target":132},{"source":181,"value":1,"target":138},{"source":181,"value":1,"target":141},{"source":181,"value":1,"target":120},{"source":181,"value":1,"target":141},{"source":181,"value":1,"target":120},{"source":181,"value":1,"target":118},{"source":181,"value":1,"target":141},{"source":181,"value":1,"target":120},{"source":181,"value":1,"target":118},{"source":181,"value":1,"target":141},{"source":181,"value":1,"target":120},{"source":181,"value":1,"target":118},{"source":181,"value":1,"target":141},{"source":181,"value":1,"target":122},{"source":181,"value":1,"target":120},{"source":181,"value":1,"target":118},{"source":181,"value":1,"target":136},{"source":181,"value":1,"target":141},{"source":181,"value":1,"target":120},{"source":181,"value":1,"target":118},{"source":181,"value":1,"target":141},{"source":181,"value":1,"target":120},{"source":181,"value":1,"target":118},{"source":181,"value":1,"target":141},{"source":181,"value":1,"target":120},{"source":181,"value":1,"target":118},{"source":181,"value":1,"target":141},{"source":181,"value":1,"target":120},{"source":181,"value":1,"target":126},{"source":181,"value":1,"target":122},{"source":181,"value":1,"target":136},{"source":181,"value":1,"target":141},{"source":181,"value":1,"target":120},{"source":181,"value":1,"target":141},{"source":181,"value":1,"target":120},{"source":181,"value":1,"target":141},{"source":181,"value":1,"target":120},{"source":181,"value":1,"target":130},{"source":181,"value":1,"target":141},{"source":181,"value":1,"target":120},{"source":181,"value":1,"target":130},{"source":181,"value":1,"target":141},{"source":181,"value":1,"target":120},{"source":181,"value":1,"target":118},{"source":181,"value":1,"target":141},{"source":181,"value":1,"target":182},{"source":181,"value":1,"target":183},{"source":182,"value":1,"target":174},{"source":172,"value":1,"target":119},{"source":172,"value":1,"target":104},{"source":172,"value":1,"target":106},{"source":172,"value":1,"target":87},{"source":172,"value":1,"target":92},{"source":172,"value":1,"target":119},{"source":172,"value":1,"target":104},{"source":172,"value":1,"target":106},{"source":172,"value":1,"target":87},{"source":172,"value":1,"target":92},{"source":172,"value":1,"target":119},{"source":172,"value":1,"target":119},{"source":172,"value":1,"target":119},{"source":172,"value":1,"target":119},{"source":172,"value":1,"target":96},{"source":172,"value":1,"target":119},{"source":172,"value":1,"target":119},{"source":172,"value":1,"target":119},{"source":172,"value":1,"target":119},{"source":172,"value":1,"target":96},{"source":172,"value":1,"target":158},{"source":172,"value":1,"target":158},{"source":172,"value":1,"target":171},{"source":172,"value":1,"target":170},{"source":172,"value":1,"target":170},{"source":172,"value":1,"target":30},{"source":172,"value":1,"target":30},{"source":172,"value":1,"target":158},{"source":172,"value":1,"target":158},{"source":172,"value":1,"target":158},{"source":172,"value":1,"target":158},{"source":172,"value":1,"target":30},{"source":172,"value":1,"target":30},{"source":172,"value":1,"target":113},{"source":172,"value":1,"target":114},{"source":172,"value":1,"target":119},{"source":172,"value":1,"target":114},{"source":172,"value":1,"target":89},{"source":172,"value":1,"target":163},{"source":172,"value":1,"target":89},{"source":172,"value":1,"target":163},{"source":172,"value":1,"target":163},{"source":172,"value":1,"target":171},{"source":172,"value":1,"target":113},{"source":172,"value":1,"target":114},{"source":172,"value":1,"target":119},{"source":172,"value":1,"target":114},{"source":172,"value":1,"target":89},{"source":172,"value":1,"target":163},{"source":172,"value":1,"target":89},{"source":172,"value":1,"target":163},{"source":172,"value":1,"target":116},{"source":172,"value":1,"target":163},{"source":172,"value":1,"target":113},{"source":172,"value":1,"target":114},{"source":172,"value":1,"target":119},{"source":172,"value":1,"target":114},{"source":172,"value":1,"target":89},{"source":172,"value":1,"target":163},{"source":172,"value":1,"target":89},{"source":172,"value":1,"target":163},{"source":172,"value":1,"target":163},{"source":172,"value":1,"target":171},{"source":172,"value":1,"target":113},{"source":172,"value":1,"target":114},{"source":172,"value":1,"target":119},{"source":172,"value":1,"target":114},{"source":172,"value":1,"target":89},{"source":172,"value":1,"target":163},{"source":172,"value":1,"target":89},{"source":172,"value":1,"target":163},{"source":172,"value":1,"target":116},{"source":172,"value":1,"target":163},{"source":172,"value":1,"target":119},{"source":172,"value":1,"target":88},{"source":172,"value":1,"target":89},{"source":172,"value":1,"target":119},{"source":172,"value":1,"target":88},{"source":172,"value":1,"target":89},{"source":172,"value":1,"target":119},{"source":172,"value":1,"target":107},{"source":172,"value":1,"target":119},{"source":172,"value":1,"target":107},{"source":172,"value":1,"target":119},{"source":172,"value":1,"target":86},{"source":172,"value":1,"target":107},{"source":172,"value":1,"target":119},{"source":172,"value":1,"target":86},{"source":172,"value":1,"target":107},{"source":172,"value":1,"target":119},{"source":172,"value":1,"target":86},{"source":172,"value":1,"target":107},{"source":172,"value":1,"target":90},{"source":172,"value":1,"target":119},{"source":172,"value":1,"target":86},{"source":172,"value":1,"target":107},{"source":172,"value":1,"target":90},{"source":172,"value":1,"target":88},{"source":172,"value":1,"target":119},{"source":172,"value":1,"target":107},{"source":172,"value":1,"target":88},{"source":172,"value":1,"target":119},{"source":172,"value":1,"target":107},{"source":172,"value":1,"target":119},{"source":172,"value":1,"target":85},{"source":172,"value":1,"target":119},{"source":172,"value":1,"target":85},{"source":172,"value":1,"target":109},{"source":172,"value":1,"target":109},{"source":173,"value":1,"target":76},{"source":173,"value":1,"target":76},{"source":173,"value":1,"target":172},{"source":174,"value":1,"target":76},{"source":174,"value":1,"target":76},{"source":174,"value":1,"target":172},{"source":170,"value":1,"target":161},{"source":170,"value":1,"target":162},{"source":170,"value":1,"target":161},{"source":170,"value":1,"target":162},{"source":170,"value":1,"target":161},{"source":170,"value":1,"target":162},{"source":170,"value":1,"target":161},{"source":170,"value":1,"target":162},{"source":170,"value":1,"target":175},{"source":170,"value":1,"target":54},{"source":170,"value":1,"target":112},{"source":170,"value":1,"target":176},{"source":170,"value":1,"target":54},{"source":170,"value":1,"target":112},{"source":170,"value":1,"target":177},{"source":170,"value":1,"target":178},{"source":170,"value":1,"target":179},{"source":178,"value":1,"target":161},{"source":178,"value":1,"target":162},{"source":178,"value":1,"target":55},{"source":178,"value":1,"target":179},{"source":178,"value":1,"target":55},{"source":177,"value":1,"target":161},{"source":177,"value":1,"target":162},{"source":177,"value":1,"target":56},{"source":177,"value":1,"target":179},{"source":177,"value":1,"target":56},{"source":175,"value":1,"target":161},{"source":175,"value":1,"target":162},{"source":175,"value":1,"target":35},{"source":175,"value":1,"target":30},{"source":175,"value":1,"target":160},{"source":175,"value":1,"target":54},{"source":176,"value":1,"target":161},{"source":176,"value":1,"target":162},{"source":176,"value":1,"target":35},{"source":176,"value":1,"target":160},{"source":176,"value":1,"target":54},{"source":179,"value":1,"target":161},{"source":179,"value":1,"target":162}],"stacklinks":[{"source":53,"value":1,"target":164},{"source":164,"value":1,"target":163},{"source":163,"value":1,"target":172},{"source":172,"value":1,"target":174},{"source":174,"value":1,"target":182},{"source":182,"value":1,"target":181}],"objects":[{"group":0,"y":544,"x":989},{"group":0,"y":253,"x":644},{"group":0,"y":344,"x":670},{"group":0,"y":523,"x":22},{"group":0,"y":371,"x":819},{"group":0,"y":271,"x":629},{"group":0,"y":51,"x":443},{"group":0,"y":506,"x":11},{"group":0,"y":290,"x":399},{"group":0,"y":174,"x":24},{"group":0,"y":98,"x":323},{"group":0,"y":289,"x":177},{"group":0,"y":566,"x":269},{"group":0,"y":521,"x":1161},{"group":0,"y":581,"x":494},{"group":0,"y":493,"x":340},{"group":0,"y":207,"x":208},{"group":0,"y":487,"x":573},{"group":0,"y":606,"x":275},{"group":0,"y":365,"x":134},{"group":0,"y":19,"x":20},{"group":0,"y":165,"x":949},{"group":0,"y":668,"x":1132},{"group":0,"y":232,"x":776},{"group":0,"y":564,"x":313},{"group":0,"y":223,"x":376},{"group":0,"y":615,"x":247},{"group":0,"y":521,"x":547},{"group":0,"y":320,"x":411},{"group":0,"y":513,"x":875},{"group":0,"y":142,"x":355},{"group":0,"y":124,"x":837},{"group":0,"y":448,"x":59},{"group":0,"y":351,"x":85},{"group":0,"y":222,"x":528},{"group":0,"y":425,"x":459},{"group":0,"y":390,"x":261},{"group":0,"y":411,"x":591},{"group":0,"y":181,"x":487},{"group":0,"y":154,"x":330},{"group":0,"y":432,"x":925},{"group":0,"y":682,"x":1179},{"group":0,"y":508,"x":68},{"group":0,"y":173,"x":99},{"group":0,"y":156,"x":626},{"group":0,"y":474,"x":805},{"group":0,"y":593,"x":293},{"group":0,"y":496,"x":457},{"group":0,"y":585,"x":723},{"group":0,"y":356,"x":912},{"group":0,"y":547,"x":40},{"group":0,"y":619,"x":659},{"group":0,"y":204,"x":717},{"group":0,"y":324,"x":1069},{"group":0,"y":131,"x":124},{"group":0,"y":300,"x":1000},{"group":0,"y":41,"x":717},{"group":0,"y":667,"x":1182},{"group":0,"y":47,"x":1172},{"group":0,"y":532,"x":1166},{"group":0,"y":398,"x":172},{"group":0,"y":138,"x":28},{"group":0,"y":221,"x":546},{"group":0,"y":610,"x":950},{"group":0,"y":646,"x":641},{"group":0,"y":125,"x":296},{"group":0,"y":540,"x":421},{"group":0,"y":376,"x":422},{"group":0,"y":599,"x":490},{"group":0,"y":428,"x":287},{"group":0,"y":249,"x":745},{"group":0,"y":527,"x":859},{"group":0,"y":639,"x":452},{"group":0,"y":366,"x":938},{"group":0,"y":616,"x":1145},{"group":0,"y":245,"x":299},{"group":0,"y":268,"x":1055},{"group":0,"y":271,"x":24},{"group":0,"y":197,"x":655},{"group":0,"y":310,"x":723},{"group":0,"y":236,"x":1168},{"group":0,"y":419,"x":149},{"group":0,"y":523,"x":844},{"group":0,"y":21,"x":992},{"group":0,"y":268,"x":489},{"group":0,"y":582,"x":545},{"group":0,"y":116,"x":354},{"group":0,"y":637,"x":232},{"group":0,"y":226,"x":796},{"group":0,"y":617,"x":717},{"group":0,"y":273,"x":818},{"group":0,"y":185,"x":301},{"group":0,"y":266,"x":777},{"group":0,"y":326,"x":1117},{"group":0,"y":607,"x":1002},{"group":0,"y":536,"x":426},{"group":0,"y":85,"x":1124},{"group":0,"y":591,"x":1151},{"group":0,"y":588,"x":768},{"group":0,"y":285,"x":747},{"group":0,"y":135,"x":964},{"group":0,"y":186,"x":1160},{"group":1,"y":360,"x":42},{"group":1,"y":445,"x":236},{"group":1,"y":420,"x":863},{"group":1,"y":429,"x":1156},{"group":1,"y":366,"x":480},{"group":1,"y":494,"x":1067},{"group":1,"y":340,"x":455},{"group":1,"y":628,"x":973},{"group":1,"y":52,"x":648},{"group":1,"y":138,"x":1168},{"group":1,"y":318,"x":1162},{"group":1,"y":38,"x":451},{"group":1,"y":442,"x":116},{"group":1,"y":38,"x":1107},{"group":1,"y":537,"x":1030},{"group":1,"y":131,"x":718},{"group":1,"y":524,"x":247},{"group":1,"y":657,"x":1065},{"group":1,"y":684,"x":147},{"group":1,"y":306,"x":456},{"group":1,"y":140,"x":759},{"group":1,"y":63,"x":1068},{"group":1,"y":299,"x":461},{"group":1,"y":72,"x":450},{"group":1,"y":636,"x":820},{"group":1,"y":137,"x":773},{"group":1,"y":453,"x":595},{"group":1,"y":172,"x":1078},{"group":1,"y":670,"x":1100},{"group":1,"y":329,"x":709},{"group":1,"y":455,"x":678},{"group":1,"y":325,"x":654},{"group":1,"y":390,"x":395},{"group":1,"y":231,"x":566},{"group":1,"y":35,"x":602},{"group":1,"y":293,"x":397},{"group":1,"y":475,"x":626},{"group":1,"y":140,"x":97},{"group":1,"y":324,"x":152},{"group":1,"y":270,"x":444},{"group":1,"y":182,"x":1105},{"group":1,"y":121,"x":329},{"group":1,"y":191,"x":631},{"group":1,"y":444,"x":621},{"group":1,"y":275,"x":648},{"group":1,"y":227,"x":36},{"group":1,"y":628,"x":1164},{"group":1,"y":173,"x":950},{"group":1,"y":654,"x":958},{"group":1,"y":337,"x":537},{"group":1,"y":491,"x":630},{"group":1,"y":246,"x":102},{"group":1,"y":274,"x":70},{"group":1,"y":20,"x":617},{"group":1,"y":16,"x":874},{"group":1,"y":517,"x":965},{"group":1,"y":651,"x":1043},{"group":1,"y":83,"x":505},{"group":1,"y":378,"x":599},{"group":1,"y":258,"x":1134},{"group":1,"y":254,"x":778},{"group":1,"y":657,"x":723},{"group":1,"y":562,"x":359},{"group":1,"y":50,"x":557},{"group":1,"y":367,"x":855},{"group":1,"y":137,"x":454},{"group":1,"y":302,"x":933},{"group":1,"y":270,"x":1000},{"group":1,"y":353,"x":228},{"group":1,"y":281,"x":426},{"group":1,"y":544,"x":696},{"group":1,"y":141,"x":852},{"group":1,"y":96,"x":186},{"group":1,"y":688,"x":212},{"group":1,"y":394,"x":188},{"group":1,"y":127,"x":109},{"group":1,"y":160,"x":739},{"group":1,"y":133,"x":44},{"group":1,"y":187,"x":118},{"group":1,"y":437,"x":148},{"group":1,"y":573,"x":1040},{"group":1,"y":596,"x":930},{"group":1,"y":522,"x":701},{"group":1,"y":358,"x":1029},{"group":1,"y":198,"x":866},{"group":1,"y":413,"x":302},{"group":1,"y":61,"x":837},{"group":1,"y":468,"x":646},{"group":1,"y":62,"x":578},{"group":1,"y":74,"x":919},{"group":1,"y":113,"x":223},{"group":1,"y":608,"x":714},{"group":1,"y":382,"x":1098},{"group":1,"y":120,"x":134},{"group":1,"y":615,"x":265},{"group":1,"y":148,"x":153},{"group":1,"y":600,"x":640},{"group":1,"y":544,"x":445},{"group":1,"y":466,"x":443},{"group":1,"y":39,"x":531},{"group":1,"y":118,"x":340},{"group":1,"y":523,"x":347},{"group":1,"y":71,"x":805},{"group":1,"y":215,"x":212},{"group":1,"y":237,"x":1048},{"group":1,"y":221,"x":121},{"group":1,"y":342,"x":332},{"group":1,"y":126,"x":983},{"group":1,"y":297,"x":556},{"group":1,"y":547,"x":332},{"group":1,"y":325,"x":796},{"group":1,"y":580,"x":828},{"group":1,"y":518,"x":784},{"group":1,"y":616,"x":271},{"group":1,"y":148,"x":829},{"group":1,"y":416,"x":848},{"group":1,"y":224,"x":215},{"group":1,"y":375,"x":318},{"group":1,"y":219,"x":1162},{"group":1,"y":361,"x":307},{"group":1,"y":171,"x":192},{"group":1,"y":119,"x":453},{"group":1,"y":357,"x":487},{"group":1,"y":280,"x":891},{"group":1,"y":507,"x":283},{"group":1,"y":156,"x":15},{"group":1,"y":30,"x":1006},{"group":1,"y":151,"x":1138},{"group":1,"y":361,"x":822},{"group":1,"y":638,"x":388},{"group":1,"y":401,"x":912},{"group":1,"y":376,"x":789},{"group":1,"y":452,"x":122},{"group":1,"y":10,"x":1134},{"group":1,"y":315,"x":898},{"group":1,"y":148,"x":471},{"group":1,"y":201,"x":258},{"group":1,"y":618,"x":646},{"group":1,"y":263,"x":707},{"group":1,"y":259,"x":418},{"group":1,"y":211,"x":826},{"group":1,"y":635,"x":877},{"group":1,"y":103,"x":751},{"group":1,"y":137,"x":943},{"group":1,"y":506,"x":1161},{"group":1,"y":95,"x":379},{"group":1,"y":311,"x":125},{"group":1,"y":540,"x":190},{"group":1,"y":302,"x":937},{"group":1,"y":590,"x":324},{"group":1,"y":361,"x":118},{"group":1,"y":615,"x":379},{"group":1,"y":293,"x":294},{"group":1,"y":584,"x":616},{"group":1,"y":463,"x":771},{"group":1,"y":398,"x":919},{"group":1,"y":95,"x":1145},{"group":1,"y":59,"x":525},{"group":1,"y":497,"x":663},{"group":1,"y":283,"x":881},{"group":1,"y":373,"x":437},{"group":1,"y":429,"x":397},{"group":1,"y":44,"x":512},{"group":1,"y":235,"x":941},{"group":1,"y":624,"x":1113},{"group":1,"y":383,"x":905},{"group":1,"y":565,"x":449},{"group":1,"y":60,"x":111},{"group":1,"y":445,"x":831},{"group":1,"y":446,"x":246},{"group":1,"y":58,"x":376},{"group":1,"y":463,"x":843},{"group":1,"y":576,"x":892},{"group":1,"y":132,"x":761},{"group":1,"y":124,"x":345},{"group":1,"y":543,"x":545},{"group":1,"y":341,"x":598},{"group":1,"y":306,"x":1172},{"group":1,"y":286,"x":843},{"group":1,"y":60,"x":340},{"group":1,"y":663,"x":1049},{"group":1,"y":94,"x":973},{"group":1,"y":632,"x":434},{"group":1,"y":648,"x":450},{"group":1,"y":67,"x":19},{"group":1,"y":343,"x":640},{"group":1,"y":193,"x":782},{"group":1,"y":246,"x":375},{"group":2,"y":350,"x":163},{"group":2,"y":318,"x":622},{"group":2,"y":445,"x":798},{"group":2,"y":326,"x":117},{"group":2,"y":428,"x":64},{"group":2,"y":491,"x":649},{"group":2,"y":536,"x":1133},{"group":2,"y":102,"x":890},{"group":2,"y":392,"x":447},{"group":2,"y":597,"x":1058},{"group":2,"y":98,"x":604},{"group":2,"y":464,"x":413},{"group":2,"y":191,"x":1077},{"group":2,"y":438,"x":653},{"group":2,"y":590,"x":408},{"group":2,"y":120,"x":247},{"group":2,"y":102,"x":697},{"group":2,"y":380,"x":882},{"group":2,"y":73,"x":82},{"group":2,"y":41,"x":1112},{"group":2,"y":627,"x":748},{"group":2,"y":103,"x":105},{"group":2,"y":180,"x":221},{"group":2,"y":630,"x":958},{"group":2,"y":393,"x":33},{"group":3,"y":184,"x":793},{"group":3,"y":260,"x":391},{"group":3,"y":219,"x":168},{"group":3,"y":27,"x":32},{"group":3,"y":489,"x":1179},{"group":3,"y":424,"x":1013},{"group":3,"y":449,"x":522},{"group":3,"y":575,"x":667},{"group":3,"y":171,"x":323},{"group":3,"y":452,"x":614},{"group":3,"y":396,"x":460},{"group":3,"y":619,"x":517},{"group":3,"y":349,"x":574},{"group":3,"y":240,"x":172},{"group":3,"y":378,"x":93},{"group":3,"y":618,"x":1032},{"group":3,"y":330,"x":27},{"group":3,"y":33,"x":347},{"group":3,"y":585,"x":956},{"group":3,"y":585,"x":572},{"group":3,"y":501,"x":132},{"group":3,"y":412,"x":443},{"group":3,"y":137,"x":648},{"group":3,"y":292,"x":1054},{"group":3,"y":504,"x":1045},{"group":3,"y":37,"x":1017},{"group":3,"y":491,"x":888},{"group":3,"y":358,"x":359},{"group":4,"y":194,"x":893},{"group":4,"y":582,"x":187},{"group":4,"y":435,"x":319},{"group":4,"y":35,"x":527},{"group":4,"y":497,"x":320},{"group":4,"y":196,"x":1162},{"group":4,"y":200,"x":370},{"group":4,"y":635,"x":560},{"group":4,"y":263,"x":401},{"group":4,"y":326,"x":164},{"group":4,"y":120,"x":876},{"group":4,"y":262,"x":295},{"group":4,"y":306,"x":903},{"group":4,"y":24,"x":907},{"group":4,"y":346,"x":536},{"group":4,"y":227,"x":1018},{"group":4,"y":525,"x":298},{"group":4,"y":75,"x":513},{"group":4,"y":545,"x":466},{"group":4,"y":341,"x":185},{"group":4,"y":309,"x":176},{"group":4,"y":552,"x":173},{"group":4,"y":562,"x":481},{"group":4,"y":667,"x":158},{"group":4,"y":306,"x":1162},{"group":4,"y":180,"x":518},{"group":4,"y":177,"x":815},{"group":4,"y":492,"x":808},{"group":4,"y":53,"x":1120},{"group":4,"y":431,"x":97},{"group":4,"y":329,"x":294},{"group":4,"y":533,"x":584},{"group":4,"y":232,"x":456},{"group":4,"y":345,"x":966},{"group":4,"y":164,"x":256},{"group":4,"y":500,"x":21},{"group":4,"y":399,"x":1175},{"group":4,"y":191,"x":105},{"group":4,"y":464,"x":852},{"group":4,"y":55,"x":205},{"group":4,"y":643,"x":86},{"group":4,"y":454,"x":954},{"group":4,"y":647,"x":706},{"group":4,"y":557,"x":248},{"group":4,"y":92,"x":80},{"group":4,"y":577,"x":865},{"group":4,"y":514,"x":395},{"group":4,"y":244,"x":1141},{"group":4,"y":270,"x":1167},{"group":4,"y":380,"x":1029},{"group":4,"y":80,"x":463},{"group":4,"y":230,"x":291},{"group":4,"y":346,"x":448},{"group":4,"y":498,"x":155},{"group":4,"y":398,"x":448},{"group":4,"y":685,"x":596},{"group":4,"y":387,"x":796},{"group":4,"y":324,"x":807},{"group":4,"y":56,"x":279},{"group":4,"y":170,"x":734},{"group":4,"y":229,"x":76},{"group":4,"y":351,"x":1075},{"group":4,"y":553,"x":513},{"group":4,"y":378,"x":1163},{"group":4,"y":643,"x":448},{"group":4,"y":385,"x":1028},{"group":4,"y":596,"x":609},{"group":4,"y":658,"x":1160},{"group":4,"y":421,"x":386},{"group":4,"y":17,"x":1164},{"group":4,"y":507,"x":1175},{"group":4,"y":425,"x":587},{"group":4,"y":68,"x":1004},{"group":4,"y":277,"x":90},{"group":4,"y":283,"x":630},{"group":4,"y":350,"x":585},{"group":4,"y":86,"x":768},{"group":4,"y":677,"x":872},{"group":4,"y":516,"x":51},{"group":4,"y":359,"x":934},{"group":4,"y":192,"x":223},{"group":4,"y":533,"x":41},{"group":4,"y":635,"x":104},{"group":4,"y":200,"x":823},{"group":4,"y":352,"x":794},{"group":4,"y":86,"x":380},{"group":4,"y":651,"x":489},{"group":4,"y":258,"x":114},{"group":4,"y":153,"x":999},{"group":4,"y":523,"x":807},{"group":4,"y":467,"x":903},{"group":4,"y":21,"x":871},{"group":4,"y":363,"x":1006},{"group":4,"y":20,"x":590},{"group":4,"y":653,"x":264},{"group":4,"y":592,"x":525},{"group":4,"y":563,"x":867},{"group":4,"y":354,"x":498},{"group":4,"y":114,"x":61},{"group":4,"y":230,"x":218},{"group":4,"y":159,"x":622},{"group":4,"y":564,"x":1012},{"group":4,"y":355,"x":888},{"group":4,"y":445,"x":860},{"group":4,"y":597,"x":331},{"group":4,"y":653,"x":1000},{"group":4,"y":244,"x":1133},{"group":4,"y":672,"x":259},{"group":4,"y":305,"x":657},{"group":4,"y":582,"x":1040},{"group":4,"y":465,"x":552},{"group":4,"y":286,"x":826},{"group":4,"y":624,"x":1163},{"group":4,"y":335,"x":444},{"group":4,"y":420,"x":825},{"group":4,"y":652,"x":919},{"group":4,"y":74,"x":878},{"group":4,"y":544,"x":741},{"group":4,"y":539,"x":34},{"group":4,"y":266,"x":281},{"group":4,"y":628,"x":329},{"group":4,"y":430,"x":384},{"group":4,"y":484,"x":659},{"group":4,"y":625,"x":965},{"group":4,"y":385,"x":568},{"group":4,"y":176,"x":283},{"group":4,"y":86,"x":1011},{"group":4,"y":218,"x":1169},{"group":4,"y":320,"x":115},{"group":4,"y":105,"x":688},{"group":4,"y":48,"x":613},{"group":4,"y":236,"x":283},{"group":4,"y":319,"x":617},{"group":4,"y":218,"x":1092},{"group":4,"y":302,"x":184},{"group":4,"y":113,"x":940},{"group":4,"y":470,"x":1140},{"group":4,"y":167,"x":701},{"group":4,"y":667,"x":690},{"group":4,"y":357,"x":849},{"group":4,"y":672,"x":809},{"group":4,"y":451,"x":491},{"group":4,"y":430,"x":861},{"group":4,"y":396,"x":398},{"group":4,"y":529,"x":803},{"group":4,"y":114,"x":30},{"group":4,"y":282,"x":693},{"group":4,"y":24,"x":1101},{"group":4,"y":658,"x":34},{"group":4,"y":108,"x":334},{"group":4,"y":42,"x":991},{"group":4,"y":618,"x":437},{"group":4,"y":536,"x":742},{"group":4,"y":201,"x":319},{"group":4,"y":484,"x":881},{"group":4,"y":189,"x":831},{"group":4,"y":105,"x":983},{"group":4,"y":208,"x":965},{"group":4,"y":122,"x":485},{"group":4,"y":41,"x":220},{"group":4,"y":270,"x":204},{"group":4,"y":532,"x":155},{"group":4,"y":364,"x":855},{"group":4,"y":590,"x":677},{"group":4,"y":43,"x":1172},{"group":4,"y":40,"x":206},{"group":4,"y":241,"x":680},{"group":4,"y":533,"x":856},{"group":4,"y":228,"x":517},{"group":4,"y":159,"x":1183},{"group":4,"y":495,"x":700},{"group":4,"y":609,"x":280},{"group":4,"y":345,"x":261},{"group":4,"y":321,"x":753},{"group":4,"y":550,"x":227},{"group":4,"y":336,"x":187},{"group":4,"y":44,"x":244},{"group":4,"y":535,"x":739},{"group":4,"y":162,"x":79},{"group":4,"y":426,"x":355},{"group":4,"y":369,"x":229},{"group":4,"y":687,"x":192},{"group":4,"y":13,"x":362},{"group":4,"y":478,"x":1122},{"group":4,"y":414,"x":834},{"group":4,"y":189,"x":162},{"group":4,"y":57,"x":219},{"group":4,"y":588,"x":184},{"group":4,"y":224,"x":439},{"group":4,"y":151,"x":308},{"group":4,"y":675,"x":948},{"group":4,"y":460,"x":1040},{"group":4,"y":471,"x":1093},{"group":4,"y":259,"x":554},{"group":4,"y":317,"x":928},{"group":4,"y":12,"x":1079},{"group":4,"y":642,"x":706},{"group":4,"y":204,"x":940},{"group":4,"y":361,"x":204},{"group":4,"y":218,"x":134},{"group":4,"y":269,"x":164},{"group":4,"y":391,"x":1039},{"group":4,"y":636,"x":145},{"group":4,"y":682,"x":1147},{"group":4,"y":396,"x":855},{"group":4,"y":176,"x":475},{"group":4,"y":518,"x":990},{"group":4,"y":79,"x":23},{"group":4,"y":171,"x":1050},{"group":4,"y":207,"x":1001},{"group":4,"y":554,"x":15},{"group":4,"y":271,"x":891},{"group":4,"y":591,"x":1084},{"group":4,"y":347,"x":971},{"group":4,"y":233,"x":1043},{"group":4,"y":63,"x":1117},{"group":4,"y":23,"x":1030},{"group":4,"y":249,"x":822},{"group":4,"y":199,"x":27},{"group":4,"y":139,"x":139},{"group":4,"y":200,"x":490},{"group":4,"y":94,"x":148},{"group":4,"y":311,"x":1185},{"group":5,"y":146,"x":194},{"group":5,"y":138,"x":358},{"group":5,"y":317,"x":51},{"group":5,"y":208,"x":1175},{"group":5,"y":481,"x":623},{"group":5,"y":547,"x":598},{"group":5,"y":343,"x":111},{"group":5,"y":265,"x":628},{"group":6,"y":367,"x":555},{"group":6,"y":30,"x":155},{"group":6,"y":79,"x":666},{"group":6,"y":278,"x":996},{"group":7,"y":278,"x":682},{"group":7,"y":439,"x":160},{"group":7,"y":471,"x":307},{"group":7,"y":134,"x":136},{"group":7,"y":361,"x":1035},{"group":7,"y":685,"x":340},{"group":7,"y":531,"x":462},{"group":7,"y":306,"x":290},{"group":7,"y":552,"x":87},{"group":7,"y":458,"x":1109},{"group":7,"y":338,"x":1183},{"group":7,"y":137,"x":62},{"group":7,"y":228,"x":712}]}