{"nodes":[{"name":"getConnection","highlight":"t","group":0,"y":226,"x":473},{"name":"addBook","highlight":"f","group":1,"y":260,"x":484},{"name":"getBooks","highlight":"f","group":1,"y":196,"x":510},{"name":"addBorrower","highlight":"f","group":1,"y":189,"x":324},{"name":"placeHold","highlight":"f","group":1,"y":283,"x":335},{"name":"checkOut","highlight":"f","group":1,"y":308,"x":414},{"name":"returnBook","highlight":"f","group":1,"y":320,"x":315},{"name":"payFine","highlight":"f","group":1,"y":287,"x":629},{"name":"getInfoBorrowedItems","highlight":"f","group":1,"y":282,"x":543},{"name":"getInfoHeldItems","highlight":"f","group":1,"y":245,"x":584},{"name":"getInfoFines","highlight":"f","group":1,"y":277,"x":475},{"name":"mainLib","highlight":"f","group":1,"y":349,"x":361},{"name":"connect","highlight":"f","group":2,"y":348,"x":595},{"name":"actionPerformed","highlight":"f","group":3,"y":248,"x":326},{"name":"run","highlight":"f","group":3,"y":272,"x":471},{"name":"access$000","highlight":"f","group":4,"y":296,"x":424},{"name":"getCodeBase","highlight":"f","group":4,"y":285,"x":586},{"name":"build","highlight":"f","group":4,"y":195,"x":559},{"name":"parseArgs","highlight":"f","group":4,"y":323,"x":323},{"name":"isActive","highlight":"f","group":4,"y":250,"x":337},{"name":"getDocumentBase","highlight":"f","group":4,"y":156,"x":552},{"name":"getParameter","highlight":"f","group":4,"y":336,"x":313},{"name":"appletResize","highlight":"f","group":4,"y":291,"x":627},{"name":"getAppletContext","highlight":"f","group":4,"y":303,"x":470},{"name":"getAudioClip","highlight":"f","group":4,"y":293,"x":289},{"name":"getImage","highlight":"f","group":4,"y":278,"x":505},{"name":"getApplet","highlight":"f","group":4,"y":212,"x":412},{"name":"getApplets","highlight":"f","group":4,"y":171,"x":256},{"name":"showDocument","highlight":"f","group":4,"y":165,"x":287},{"name":"showDocument","highlight":"f","group":4,"y":314,"x":481},{"name":"showStatus","highlight":"f","group":4,"y":225,"x":638},{"name":"setStream","highlight":"f","group":4,"y":251,"x":256},{"name":"getStream","highlight":"f","group":4,"y":318,"x":408},{"name":"getStreamKeys","highlight":"f","group":4,"y":304,"x":511},{"name":"addFileMenuItem","highlight":"f","group":4,"y":269,"x":549},{"name":"addLibraryMenuItem","highlight":"f","group":5,"y":220,"x":464},{"name":"addBorrowerMenuItem","highlight":"f","group":5,"y":256,"x":521},{"name":"addClerkMenuItem","highlight":"f","group":5,"y":188,"x":473},{"name":"addLibrarianMenuItem","highlight":"f","group":5,"y":177,"x":425},{"name":"access$0","highlight":"f","group":5,"y":157,"x":342},{"name":"initComponents","highlight":"f","group":5,"y":216,"x":289},{"name":"access$0","highlight":"f","group":6,"y":278,"x":368},{"name":"initComponents","highlight":"f","group":6,"y":184,"x":576},{"name":"access$0","highlight":"f","group":7,"y":224,"x":515},{"name":"initComponents","highlight":"f","group":7,"y":344,"x":589},{"name":"initComponents","highlight":"f","group":8,"y":252,"x":503},{"name":"initComponents","highlight":"f","group":9,"y":207,"x":616},{"name":"initComponents","highlight":"f","group":10,"y":268,"x":623},{"name":"access$0","highlight":"f","group":11,"y":224,"x":419},{"name":"initComponents","highlight":"f","group":11,"y":302,"x":372},{"name":"initComponents","highlight":"f","group":12,"y":224,"x":412},{"name":"initComponents","highlight":"f","group":13,"y":169,"x":449},{"name":"access$0","highlight":"f","group":14,"y":151,"x":472},{"name":"initComponents","highlight":"f","group":14,"y":177,"x":505},{"name":"initComponents","highlight":"f","group":15,"y":160,"x":528}],"links":[{"source":15,"value":1,"target":14},{"source":11,"value":1,"target":14}]}