{"nodes":[{"name":"getConnection","highlight":"t","group":0,"y":321,"x":310},{"name":"addBook","highlight":"f","group":1,"y":325,"x":373},{"name":"getBooks","highlight":"f","group":1,"y":195,"x":368},{"name":"addBorrower","highlight":"f","group":1,"y":178,"x":539},{"name":"placeHold","highlight":"f","group":1,"y":282,"x":397},{"name":"checkOut","highlight":"f","group":1,"y":311,"x":359},{"name":"returnBook","highlight":"f","group":1,"y":349,"x":294},{"name":"payFine","highlight":"f","group":1,"y":220,"x":450},{"name":"getInfoBorrowedItems","highlight":"f","group":1,"y":238,"x":276},{"name":"getInfoHeldItems","highlight":"f","group":1,"y":227,"x":532},{"name":"getInfoFines","highlight":"f","group":1,"y":326,"x":577},{"name":"mainLib","highlight":"f","group":1,"y":281,"x":538},{"name":"connect","highlight":"f","group":2,"y":209,"x":305},{"name":"actionPerformed","highlight":"f","group":3,"y":155,"x":390},{"name":"run","highlight":"f","group":3,"y":222,"x":254},{"name":"access$000","highlight":"f","group":4,"y":174,"x":410},{"name":"getCodeBase","highlight":"f","group":4,"y":154,"x":523},{"name":"build","highlight":"f","group":4,"y":224,"x":546},{"name":"parseArgs","highlight":"f","group":4,"y":182,"x":512},{"name":"isActive","highlight":"f","group":4,"y":199,"x":552},{"name":"getDocumentBase","highlight":"f","group":4,"y":279,"x":400},{"name":"getParameter","highlight":"f","group":4,"y":292,"x":470},{"name":"appletResize","highlight":"f","group":4,"y":331,"x":276},{"name":"getAppletContext","highlight":"f","group":4,"y":234,"x":447},{"name":"getAudioClip","highlight":"f","group":4,"y":186,"x":552},{"name":"getImage","highlight":"f","group":4,"y":237,"x":273},{"name":"getApplet","highlight":"f","group":4,"y":330,"x":378},{"name":"getApplets","highlight":"f","group":4,"y":348,"x":524},{"name":"showDocument","highlight":"f","group":4,"y":151,"x":406},{"name":"showDocument","highlight":"f","group":4,"y":248,"x":565},{"name":"showStatus","highlight":"f","group":4,"y":289,"x":470},{"name":"setStream","highlight":"f","group":4,"y":295,"x":347},{"name":"getStream","highlight":"f","group":4,"y":226,"x":274},{"name":"getStreamKeys","highlight":"f","group":4,"y":318,"x":387},{"name":"addLibraryMenuItem","highlight":"f","group":4,"y":223,"x":349},{"name":"addBorrowerMenuItem","highlight":"f","group":5,"y":261,"x":630},{"name":"addFileMenuItem","highlight":"f","group":5,"y":191,"x":616},{"name":"addClerkMenuItem","highlight":"f","group":5,"y":315,"x":285},{"name":"addLibrarianMenuItem","highlight":"f","group":5,"y":325,"x":553},{"name":"access$0","highlight":"f","group":5,"y":263,"x":569},{"name":"access$0","highlight":"f","group":5,"y":297,"x":496},{"name":"initComponents","highlight":"f","group":6,"y":163,"x":254},{"name":"access$0","highlight":"f","group":6,"y":261,"x":632},{"name":"initComponents","highlight":"f","group":7,"y":305,"x":590},{"name":"initComponents","highlight":"f","group":7,"y":328,"x":536},{"name":"initComponents","highlight":"f","group":8,"y":185,"x":629},{"name":"initComponents","highlight":"f","group":9,"y":194,"x":514},{"name":"access$0","highlight":"f","group":10,"y":293,"x":626},{"name":"initComponents","highlight":"f","group":11,"y":261,"x":554},{"name":"initComponents","highlight":"f","group":11,"y":266,"x":324},{"name":"initComponents","highlight":"f","group":12,"y":177,"x":363},{"name":"access$0","highlight":"f","group":13,"y":157,"x":365},{"name":"initComponents","highlight":"f","group":14,"y":191,"x":443},{"name":"initComponents","highlight":"f","group":14,"y":227,"x":251},{"name":"initComponents","highlight":"f","group":15,"y":258,"x":423}],"links":[{"source":11,"value":1,"target":14}]}