{"nodes":[{"name":"getConnection","highlight":"t","group":0,"y":193,"x":292},{"name":"addBook","highlight":"f","group":1,"y":164,"x":580},{"name":"getBooks","highlight":"f","group":1,"y":181,"x":348},{"name":"addBorrower","highlight":"f","group":1,"y":228,"x":551},{"name":"placeHold","highlight":"f","group":1,"y":311,"x":304},{"name":"checkOut","highlight":"f","group":1,"y":238,"x":413},{"name":"returnBook","highlight":"f","group":1,"y":217,"x":546},{"name":"payFine","highlight":"f","group":1,"y":177,"x":386},{"name":"getInfoBorrowedItems","highlight":"f","group":1,"y":301,"x":600},{"name":"getInfoHeldItems","highlight":"f","group":1,"y":158,"x":609},{"name":"getInfoFines","highlight":"f","group":1,"y":247,"x":401},{"name":"mainLib","highlight":"f","group":1,"y":215,"x":644},{"name":"connect","highlight":"f","group":2,"y":309,"x":555},{"name":"actionPerformed","highlight":"f","group":3,"y":270,"x":454},{"name":"run","highlight":"f","group":3,"y":230,"x":436},{"name":"access$000","highlight":"f","group":4,"y":306,"x":535},{"name":"getCodeBase","highlight":"f","group":4,"y":306,"x":423},{"name":"build","highlight":"f","group":4,"y":180,"x":356},{"name":"parseArgs","highlight":"f","group":4,"y":284,"x":474},{"name":"isActive","highlight":"f","group":4,"y":283,"x":501},{"name":"getDocumentBase","highlight":"f","group":4,"y":174,"x":327},{"name":"getParameter","highlight":"f","group":4,"y":200,"x":366},{"name":"appletResize","highlight":"f","group":4,"y":312,"x":454},{"name":"getAppletContext","highlight":"f","group":4,"y":315,"x":591},{"name":"getAudioClip","highlight":"f","group":4,"y":156,"x":257},{"name":"getImage","highlight":"f","group":4,"y":169,"x":310},{"name":"getApplet","highlight":"f","group":4,"y":318,"x":588},{"name":"getApplets","highlight":"f","group":4,"y":279,"x":376},{"name":"showDocument","highlight":"f","group":4,"y":270,"x":556},{"name":"showDocument","highlight":"f","group":4,"y":214,"x":596},{"name":"showStatus","highlight":"f","group":4,"y":210,"x":376},{"name":"setStream","highlight":"f","group":4,"y":207,"x":321},{"name":"getStream","highlight":"f","group":4,"y":227,"x":279},{"name":"getStreamKeys","highlight":"f","group":4,"y":204,"x":277},{"name":"addFileMenuItem","highlight":"f","group":4,"y":319,"x":289},{"name":"addLibraryMenuItem","highlight":"f","group":5,"y":333,"x":361},{"name":"addBorrowerMenuItem","highlight":"f","group":5,"y":249,"x":600},{"name":"addClerkMenuItem","highlight":"f","group":5,"y":210,"x":389},{"name":"addLibrarianMenuItem","highlight":"f","group":5,"y":225,"x":455},{"name":"access$0","highlight":"f","group":5,"y":176,"x":271},{"name":"initComponents","highlight":"f","group":5,"y":245,"x":278},{"name":"access$0","highlight":"f","group":6,"y":238,"x":493},{"name":"initComponents","highlight":"f","group":6,"y":176,"x":488},{"name":"access$0","highlight":"f","group":7,"y":275,"x":439},{"name":"initComponents","highlight":"f","group":7,"y":270,"x":475},{"name":"initComponents","highlight":"f","group":8,"y":342,"x":413},{"name":"initComponents","highlight":"f","group":9,"y":175,"x":307},{"name":"initComponents","highlight":"f","group":10,"y":186,"x":358},{"name":"access$0","highlight":"f","group":11,"y":332,"x":614},{"name":"initComponents","highlight":"f","group":11,"y":235,"x":309},{"name":"initComponents","highlight":"f","group":12,"y":258,"x":617},{"name":"initComponents","highlight":"f","group":13,"y":311,"x":394},{"name":"access$0","highlight":"f","group":14,"y":154,"x":432},{"name":"initComponents","highlight":"f","group":14,"y":314,"x":532},{"name":"initComponents","highlight":"f","group":15,"y":202,"x":509}],"links":[{"source":12,"value":1,"target":12},{"source":0,"value":1,"target":12},{"source":12,"value":1,"target":0},{"source":0,"value":1,"target":0},{"source":0,"value":1,"target":12},{"source":11,"value":1,"target":14}]}